astroid_miner/__init__.py
astroid_miner/main.py
astroid_miner/commands/__init__.py
astroid_miner/commands/call_diagram.py
astroid_miner/commands/command.py
astroid_miner/commands/show_path.py
astroid_miner-0.0.3.dist-info/METADATA
astroid_miner-0.0.3.dist-info/WHEEL
astroid_miner-0.0.3.dist-info/entry_points.txt
astroid_miner-0.0.3.dist-info/licenses/LICENSE
astroid_miner-0.0.3.dist-info/RECORD
